[
  {
    "id": "UAVSICS-2026-0001",
    "alumno": "Macarena Moreno",
    "empresa": "Aramark",
    "curso": "eBee X",
    "horas": 30,
    "fecha": "10-07-2026",
    "instructor": "Eduardo Pérez",
    "estado": "Revocado",
    "pdf": "https://drive.google.com/file/d/1SA6_FJmiIfqN4AymTm7-VkivukjOjW4N/view?usp=drivesdk"
  },
  {
    "id": "UAVSICS-2026-0002",
    "alumno": "Jorge Poblete Santibáñez",
    "empresa": "UAVSICS",
    "curso": "Autel Alpha",
    "horas": 30,
    "fecha": "20-07-2026",
    "instructor": "Eduardo Pérez",
    "estado": "Revocado",
    "pdf": "https://drive.google.com/file/d/1sbEfF026rzCpmDzXUqtjhIkjsXs5qHMv/view?usp=drivesdk"
  },
  {
    "id": "UAVSICS-2026-0003",
    "alumno": "Eduardo Pérez Rojas",
    "empresa": "UAVSICS",
    "curso": "Autel Apex",
    "horas": 30,
    "fecha": "20-07-2026",
    "instructor": "Jorge Poblete",
    "estado": "Revocado",
    "pdf": "https://drive.google.com/file/d/14PbzkMPTYxzNvhUcyLzXjhzAaarN5uDF/view?usp=drivesdk"
  },
  {
    "id": "UAVSICS-2026-0004",
    "alumno": "Macarena Moreno Salas",
    "empresa": "Aramark",
    "curso": "WingtraRAY",
    "horas": 16,
    "fecha": "20-07-2026",
    "instructor": "Jorge Poblete",
    "estado": "Revocado",
    "pdf": "https://drive.google.com/file/d/12QevywBP5nY5ZnxLOwJZNRmqH02acgbd/view?usp=drivesdk"
  },
  {
    "id": "UAVSICS-2026-0005",
    "alumno": "Jorge Poblete Santibáñez",
    "empresa": "UAVSICS",
    "curso": "Autel Apex",
    "horas": 30,
    "fecha": "20-07-2026",
    "instructor": "Eduardo Pérez",
    "estado": "Revocado",
    "pdf": "https://drive.google.com/file/d/1QdFrLLCX9wuPduB5Y8p6JIqNFosUUJ_H/view?usp=drivesdk"
  },
  {
    "id": "UAVSICS-2026-0006",
    "alumno": "Eduardo Pérez Rojas",
    "empresa": "UAVSICS",
    "curso": "Autel EVO Max Series",
    "horas": 30,
    "fecha": "23-07-2026",
    "instructor": "Jorge Poblete",
    "estado": "Revocado",
    "pdf": "https://drive.google.com/file/d/1MQCvC7zSygHKDCkuDKJCHUP1nzXBAhEr/view?usp=drivesdk"
  },
  {
    "id": "UAVSICS-2026-0007",
    "alumno": "Eduardo Pérez Rojas",
    "empresa": "UAVSICS",
    "curso": "Autel EVO Max Series",
    "horas": 30,
    "fecha": "23-07-2026",
    "instructor": "Jorge Poblete",
    "estado": "Válido",
    "pdf": "https://drive.google.com/file/d/1qUcVv1v6VIMMngzYHO8wO02p-YUpEou6/view?usp=drivesdk"
  }
]